tempren/__init__.py
tempren/adhoc.py
tempren/alias.py
tempren/cli.py
tempren/discovery.py
tempren/evaluation.py
tempren/exceptions.py
tempren/factories.py
tempren/file_filters.py
tempren/file_sorters.py
tempren/filesystem.py
tempren/pipeline.py
tempren/primitives.py
tempren/tags/__init__.py
tempren/tags/audio.py
tempren/tags/core.py
tempren/tags/filesystem.py
tempren/tags/gpx.py
tempren/tags/hash.py
tempren/tags/image.py
tempren/tags/text.py
tempren/tags/video.py
tempren/template/__init__.py
tempren/template/ast.py
tempren/template/compiler.py
tempren/template/exceptions.py
tempren/template/generators.py
tempren/template/grammar/TagTemplateLexer.g4
tempren/template/grammar/TagTemplateLexer.interp
tempren/template/grammar/TagTemplateLexer.py
tempren/template/grammar/TagTemplateLexer.tokens
tempren/template/grammar/TagTemplateParser.g4
tempren/template/grammar/TagTemplateParser.interp
tempren/template/grammar/TagTemplateParser.py
tempren/template/grammar/TagTemplateParser.tokens
tempren/template/grammar/TagTemplateParserVisitor.py
tempren/template/grammar/__init__.py
tempren/template/grammar/generate.sh
tempren/template/grammar/generate_for_grun.sh
tempren/template/parser.py
tempren/template/registry.py
tempren-1.2.6.dist-info/LICENSE
tempren-1.2.6.dist-info/METADATA
tempren-1.2.6.dist-info/WHEEL
tempren-1.2.6.dist-info/entry_points.txt
tempren-1.2.6.dist-info/RECORD
