Metadata-Version: 2.1
Name: tempren
Version: 1.2.6
Summary: Template-based renaming utility
Home-page: https://github.com/idle-code/tempren
License: GPL-3.0-or-later
Keywords: batch-renaming,cli,filename
Author: Paweł Żukowski
Author-email: p.z.idlecode@gmail.com
Requires-Python: >=3.9,<4.0
Classifier: Development Status :: 4 - Beta
Classifier: Environment :: Console
Classifier: Intended Audience :: End Users/Desktop
Classifier: Intended Audience :: System Administrators
Classifier: License :: OSI Approved :: GNU General Public License v3 or later (GPLv3+)
Classifier: Natural Language :: English
Classifier: Operating System :: POSIX
Classifier: Operating System :: POSIX :: Linux
Classifier: Operating System :: Unix
Classifier: Programming Language :: Python :: 3
Classifier: Programming Language :: Python :: 3.9
Classifier: Programming Language :: Python :: 3.10
Classifier: Programming Language :: Python :: 3.11
Classifier: Programming Language :: Python :: 3.12
Classifier: Topic :: System :: Filesystems
Classifier: Topic :: Utilities
Provides-Extra: video
Requires-Dist: Pillow (>=10.0.0,<11.0.0)
Requires-Dist: Pint (>=0.21.0,<0.22.0)
Requires-Dist: Unidecode (>=1.3.6,<2.0.0)
Requires-Dist: antlr4-python3-runtime (==4.13.1)
Requires-Dist: docstring-parser (>=0.16,<0.17)
Requires-Dist: gpxpy (==1.5.0)
Requires-Dist: isodate (>=0.6.1,<0.7.0)
Requires-Dist: mutagen (>=1.46.0,<2.0.0)
Requires-Dist: pathvalidate (>=3.1.0,<4.0.0)
Requires-Dist: piexif (>=1.1.3,<2.0.0)
Requires-Dist: pymediainfo (>=6.0.1,<7.0.0) ; extra == "video"
Requires-Dist: python-magic (>=0.4.27,<0.5.0)
